[
  {
    "customerInfo": {
      "fullName": "HoangPHU",
      "phone": "0374378597",
      "city": "Tỉnh Quảng Ninh",
      "district": "Thị xã Quảng Yên",
      "ward": "Xã Liên Vị",
      "address": "ha noi viet nam"
    },
    "items": [
      {
        "title": "Bột rửa chén",
        "price": 89000,
        "img": "/static/media/product3.7ab2d6a0243aa8ad107e.png",
        "quantity": 1
      },
      {
        "title": "Vòi xịt phun sương",
        "price": 125000,
        "img": "/static/media/product2.42e9753b683f665a83dc.png",
        "quantity": 1
      }
    ],
    "totalAmount": 214000,
    "id": "ORDER-1743220456903",
    "createdAt": "2025-03-29T03:54:16.903Z"
  },
  {
    "customerInfo": {
      "fullName": "HoangPHU",
      "phone": "0374378597",
      "city": "Tỉnh Hà Giang",
      "district": "Huyện Quang Bình",
      "ward": "Xã Vĩ Thượng",
      "address": "ha noi viet nam"
    },
    "items": [
      {
        "title": "Bột rửa chén",
        "price": 89000,
        "img": "/static/media/product3.7ab2d6a0243aa8ad107e.png",
        "quantity": 1
      },
      {
        "title": "Vòi xịt phun sương",
        "price": 125000,
        "img": "/static/media/product2.42e9753b683f665a83dc.png",
        "quantity": 1
      }
    ],
    "totalAmount": 214000,
    "id": "ORDER-1743221118028",
    "createdAt": "2025-03-29T04:05:18.028Z"
  },
  {
    "customerInfo": {
      "fullName": "HoangPHU",
      "phone": "0374378597",
      "city": "Tỉnh Quảng Ninh",
      "district": "Thị xã Quảng Yên",
      "ward": "Phường Yên Hải",
      "address": "ha noi viet nam"
    },
    "items": [
      {
        "title": "Bột rửa chén",
        "price": 89000,
        "img": "/static/media/product3.7ab2d6a0243aa8ad107e.png",
        "quantity": 1
      },
      {
        "title": "Vòi xịt phun sương",
        "price": 125000,
        "img": "/static/media/product2.42e9753b683f665a83dc.png",
        "quantity": 1
      }
    ],
    "totalAmount": 214000,
    "id": "ORDER-1743221366154",
    "createdAt": "2025-03-29T04:09:26.154Z"
  },
  {
    "customerInfo": {
      "fullName": "HoangPHU",
      "phone": "0374378597",
      "city": "Tỉnh Quảng Ninh",
      "district": "Huyện Ba Chẽ",
      "ward": "Xã Thanh Sơn",
      "address": "ha noi viet nam"
    },
    "items": [
      {
        "title": "Bột rửa chén",
        "price": 89000,
        "img": "/static/media/product3.7ab2d6a0243aa8ad107e.png",
        "quantity": 1
      }
    ],
    "totalAmount": 89000,
    "id": "ORDER-1743222115003",
    "createdAt": "2025-03-29T04:21:55.003Z"
  }
]